tetraku/__init__.py
tetraku/models/__init__.py
tetraku/models/J1J2/__init__.py
tetraku/models/J1J2/pbc/__init__.py
tetraku/models/bcs/__init__.py
tetraku/models/bcs/square/__init__.py
tetraku/models/bcs/square/d_wave.py
tetraku/models/bcs/square/s_wave.py
tetraku/models/boson_metal/Sz.py
tetraku/models/boson_metal/__init__.py
tetraku/models/boson_metal/hopping_hamiltonian.py
tetraku/models/boson_metal/initial_state.py
tetraku/models/boson_metal/restrict_Sz.py
tetraku/models/cluster_heisenberg/__init__.py
tetraku/models/cluster_heisenberg/pbc/__init__.py
tetraku/models/free_fermion/__init__.py
tetraku/models/free_fermion/analytical.wl
tetraku/models/free_fermion/parity.py
tetraku/models/free_fermion/complex/__init__.py
tetraku/models/gibbs_J1J2/__init__.py
tetraku/models/gibbs_J1J2/hopping_hamiltonian.py
tetraku/models/gibbs_J1J2/random_configuration_initialization.py
tetraku/models/gibbs_J1J2/trivial_configuration_initialization.py
tetraku/models/gibbs_free_fermion/__init__.py
tetraku/models/gibbs_free_fermion/hopping_hamiltonian.py
tetraku/models/gibbs_heisenberg/__init__.py
tetraku/models/gibbs_heisenberg/hopping_hamiltonian.py
tetraku/models/gibbs_heisenberg/random_configuration_initialization.py
tetraku/models/gibbs_heisenberg/trivial_configuration_initialization.py
tetraku/models/gibbs_hubbard/__init__.py
tetraku/models/gibbs_hubbard/analytical.wl
tetraku/models/gibbs_hubbard/half_filling_random_configuration_initialization.py
tetraku/models/gibbs_hubbard/trivial_configuration_initialization.py
tetraku/models/gibbs_hubbard/hopping_hamiltonian/__init__.py
tetraku/models/gibbs_hubbard/hopping_hamiltonian/fix_particle_number.py
tetraku/models/gibbs_rydberg/__init__.py
tetraku/models/heisenberg/README.org
tetraku/models/heisenberg/__init__.py
tetraku/models/heisenberg/neel.py
tetraku/models/heisenberg/restrict_Sz.py
tetraku/models/heisenberg/complex/__init__.py
tetraku/models/heisenberg/pbc/__init__.py
tetraku/models/honeycomb_hubbard/N_down.py
tetraku-0.3.17.dist-info/METADATA
tetraku-0.3.17.dist-info/WHEEL
tetraku-0.3.17.dist-info/top_level.txt
tetraku-0.3.17.dist-info/RECORD
